basecon.py
BaseCon-1.0.2.dist-info/DESCRIPTION.rst
BaseCon-1.0.2.dist-info/METADATA
BaseCon-1.0.2.dist-info/RECORD
BaseCon-1.0.2.dist-info/WHEEL
BaseCon-1.0.2.dist-info/metadata.json
BaseCon-1.0.2.dist-info/top_level.txt
